aitools/__init__.py
aitools/features.py
aitools/mlearn.py
aitools/plot.py
aitools/roc.py
aitools_aimfeld-0.4.1.dist-info/METADATA
aitools_aimfeld-0.4.1.dist-info/WHEEL
aitools_aimfeld-0.4.1.dist-info/top_level.txt
aitools_aimfeld-0.4.1.dist-info/RECORD
