Metadata-Version: 2.1
Name: aitools-aimfeld
Version: 0.4.1
Summary: Python tools for datascience and AI
Home-page: https://github.com/aimfeld/aitools
Author: Adrian Imfeld
Author-email: aimfeld@aimfeld.ch
License: MIT
Platform: UNKNOWN
Classifier: Programming Language :: Python :: 3
Classifier: License :: OSI Approved :: MIT License
Classifier: Operating System :: OS Independent
